<ArGpsLocationData><Entry><id>68</id><altitude>0</altitude><altitudeMode>GroundRelative</altitudeMode><name>Gwanghwamun6</name><meshId>Gwanghwamun6</meshId><movementSmoothing>0.05</movementSmoothing><maxNumberOfLocationUpdates>0</maxNumberOfLocationUpdates><useMovingAverage>false</useMovingAverage><hideObjectUtilItIsPlaced>true</hideObjectUtilItIsPlaced><lat>37.57601736037161</lat><lng>126.97681019379769</lng></Entry><Entry><id>69</id><altitude>0</altitude><altitudeMode>GroundRelative</altitudeMode><name>Geunjeongjeon6</name><meshId>Geunjeongjeon6</meshId><movementSmoothing>0.05</movementSmoothing><maxNumberOfLocationUpdates>0</maxNumberOfLocationUpdates><useMovingAverage>false</useMovingAverage><hideObjectUtilItIsPlaced>true</hideObjectUtilItIsPlaced><lat>37.578539674878485</lat><lng>126.97698834329674</lng></Entry><Entry><id>70</id><altitude>0</altitude><altitudeMode>GroundRelative</altitudeMode><name>Gyeonghoeru6</name><meshId>Gyeonghoeru6</meshId><movementSmoothing>0.05</movementSmoothing><maxNumberOfLocationUpdates>0</maxNumberOfLocationUpdates><useMovingAverage>false</useMovingAverage><hideObjectUtilItIsPlaced>true</hideObjectUtilItIsPlaced><lat>37.57973084889086</lat><lng>126.9759719900531</lng></Entry><Entry><id>71</id><altitude>0</altitude><altitudeMode>GroundRelative</altitudeMode><name>Gangnyeongjeon6</name><meshId>Gangnyeongjeon6</meshId><movementSmoothing>0.05</movementSmoothing><maxNumberOfLocationUpdates>0</maxNumberOfLocationUpdates><useMovingAverage>false</useMovingAverage><hideObjectUtilItIsPlaced>true</hideObjectUtilItIsPlaced><lat>37.57938448091599</lat><lng>126.97701346962396</lng></Entry><Entry><id>72</id><lat>37.579381596763426</lat><lng>126.97698805708836</lng><altitude>0</altitude><altitudeMode>GroundRelative</altitudeMode><name>asd</name><meshId>dot6</meshId><movementSmoothing>0.05</movementSmoothing><maxNumberOfLocationUpdates>0</maxNumberOfLocationUpdates><useMovingAverage>false</useMovingAverage><hideObjectUtilItIsPlaced>true</hideObjectUtilItIsPlaced></Entry><Entry><id>73</id><lat>37.57938194121519</lat><lng>126.9769724102444</lng><altitude>0</altitude><altitudeMode>GroundRelative</altitudeMode><name>3qwtg</name><meshId>dot6</meshId><movementSmoothing>0.05</movementSmoothing><maxNumberOfLocationUpdates>0</maxNumberOfLocationUpdates><useMovingAverage>false</useMovingAverage><hideObjectUtilItIsPlaced>true</hideObjectUtilItIsPlaced></Entry><Entry><id>74</id><lat>37.579379874503985</lat><lng>126.97695198242099</lng><altitude>0</altitude><altitudeMode>GroundRelative</altitudeMode><name>sdv</name><meshId>dot6</meshId><movementSmoothing>0.05</movementSmoothing><maxNumberOfLocationUpdates>0</maxNumberOfLocationUpdates><useMovingAverage>false</useMovingAverage><hideObjectUtilItIsPlaced>true</hideObjectUtilItIsPlaced></Entry><Entry><id>75</id><lat>37.57937849669622</lat><lng>126.97692720824995</lng><altitude>0</altitude><altitudeMode>GroundRelative</altitudeMode><name>qwf</name><meshId>dot6</meshId><movementSmoothing>0.05</movementSmoothing><maxNumberOfLocationUpdates>0</maxNumberOfLocationUpdates><useMovingAverage>false</useMovingAverage><hideObjectUtilItIsPlaced>true</hideObjectUtilItIsPlaced></Entry><Entry><id>76</id><lat>37.57937918560047</lat><lng>126.9769015648119</lng><altitude>0</altitude><altitudeMode>GroundRelative</altitudeMode><name>q2f</name><meshId>dot6</meshId><movementSmoothing>0.05</movementSmoothing><maxNumberOfLocationUpdates>0</maxNumberOfLocationUpdates><useMovingAverage>false</useMovingAverage><hideObjectUtilItIsPlaced>true</hideObjectUtilItIsPlaced></Entry><Entry><id>77</id><lat>37.579377971773</lat><lng>126.97688240367114</lng><altitude>0</altitude><altitudeMode>GroundRelative</altitudeMode><name>sub</name><meshId>dot6</meshId><movementSmoothing>0.05</movementSmoothing><maxNumberOfLocationUpdates>0</maxNumberOfLocationUpdates><useMovingAverage>false</useMovingAverage><hideObjectUtilItIsPlaced>true</hideObjectUtilItIsPlaced></Entry><Entry><id>78</id><lat>37.579379037729026</lat><lng>126.97686266060333</lng><altitude>0</altitude><altitudeMode>GroundRelative</altitudeMode><name>12r</name><meshId>dot6</meshId><movementSmoothing>0.05</movementSmoothing><maxNumberOfLocationUpdates>0</maxNumberOfLocationUpdates><useMovingAverage>false</useMovingAverage><hideObjectUtilItIsPlaced>true</hideObjectUtilItIsPlaced></Entry><Entry><id>79</id><lat>37.579381708581025</lat><lng>126.97684484710862</lng><altitude>0</altitude><altitudeMode>GroundRelative</altitudeMode><name>12f</name><meshId>dot6</meshId><movementSmoothing>0.05</movementSmoothing><maxNumberOfLocationUpdates>0</maxNumberOfLocationUpdates><useMovingAverage>false</useMovingAverage><hideObjectUtilItIsPlaced>true</hideObjectUtilItIsPlaced></Entry><Entry><id>80</id><lat>37.579385905633146</lat><lng>126.97682607072272</lng><altitude>0</altitude><altitudeMode>GroundRelative</altitudeMode><name>asd</name><meshId>dot6</meshId><movementSmoothing>0.05</movementSmoothing><maxNumberOfLocationUpdates>0</maxNumberOfLocationUpdates><useMovingAverage>false</useMovingAverage><hideObjectUtilItIsPlaced>true</hideObjectUtilItIsPlaced></Entry><Entry><id>81</id><lat>37.57939315508585</lat><lng>126.97680247987859</lng><altitude>0</altitude><altitudeMode>GroundRelative</altitudeMode><name>sdg</name><meshId>dot6</meshId><movementSmoothing>0.05</movementSmoothing><maxNumberOfLocationUpdates>0</maxNumberOfLocationUpdates><useMovingAverage>false</useMovingAverage><hideObjectUtilItIsPlaced>true</hideObjectUtilItIsPlaced></Entry><Entry><id>82</id><lat>37.57940498313883</lat><lng>126.97678322204797</lng><altitude>0</altitude><altitudeMode>GroundRelative</altitudeMode><name>hfh</name><meshId>dot6</meshId><movementSmoothing>0.05</movementSmoothing><maxNumberOfLocationUpdates>0</maxNumberOfLocationUpdates><useMovingAverage>false</useMovingAverage><hideObjectUtilItIsPlaced>true</hideObjectUtilItIsPlaced></Entry><Entry><id>83</id><lat>37.57942558684057</lat><lng>126.97677792614331</lng><altitude>0</altitude><altitudeMode>GroundRelative</altitudeMode><name>sdbcc</name><meshId>dot6</meshId><movementSmoothing>0.05</movementSmoothing><maxNumberOfLocationUpdates>0</maxNumberOfLocationUpdates><useMovingAverage>false</useMovingAverage><hideObjectUtilItIsPlaced>true</hideObjectUtilItIsPlaced></Entry><Entry><id>84</id><lat>37.5794454274364</lat><lng>126.97677696325206</lng><altitude>0</altitude><altitudeMode>GroundRelative</altitudeMode><name>1111</name><meshId>dot6</meshId><movementSmoothing>0.05</movementSmoothing><maxNumberOfLocationUpdates>0</maxNumberOfLocationUpdates><useMovingAverage>false</useMovingAverage><hideObjectUtilItIsPlaced>true</hideObjectUtilItIsPlaced></Entry><Entry><id>85</id><lat>37.579463360277956</lat><lng>126.97677792614331</lng><altitude>0</altitude><altitudeMode>GroundRelative</altitudeMode><name>2222</name><meshId>dot6</meshId><movementSmoothing>0.05</movementSmoothing><maxNumberOfLocationUpdates>0</maxNumberOfLocationUpdates><useMovingAverage>false</useMovingAverage><hideObjectUtilItIsPlaced>true</hideObjectUtilItIsPlaced></Entry><Entry><id>86</id><lat>37.57948434551233</lat><lng>126.9767764818074</lng><altitude>0</altitude><altitudeMode>GroundRelative</altitudeMode><name>3333</name><meshId>dot6</meshId><movementSmoothing>0.05</movementSmoothing><maxNumberOfLocationUpdates>0</maxNumberOfLocationUpdates><useMovingAverage>false</useMovingAverage><hideObjectUtilItIsPlaced>true</hideObjectUtilItIsPlaced></Entry><Entry><id>87</id><lat>37.57950008087704</lat><lng>126.97675354557396</lng><altitude>0</altitude><altitudeMode>GroundRelative</altitudeMode><name>sdgv</name><meshId>dot6</meshId><movementSmoothing>0.05</movementSmoothing><maxNumberOfLocationUpdates>0</maxNumberOfLocationUpdates><useMovingAverage>false</useMovingAverage><hideObjectUtilItIsPlaced>true</hideObjectUtilItIsPlaced></Entry><Entry><id>88</id><lat>37.57950269089234</lat><lng>126.97673131538198</lng><altitude>0</altitude><altitudeMode>GroundRelative</altitudeMode><name>12r</name><meshId>dot6</meshId><movementSmoothing>0.05</movementSmoothing><maxNumberOfLocationUpdates>0</maxNumberOfLocationUpdates><useMovingAverage>false</useMovingAverage><hideObjectUtilItIsPlaced>true</hideObjectUtilItIsPlaced></Entry><Entry><id>89</id><lat>37.5795037783988</lat><lng>126.97670990852856</lng><altitude>0</altitude><altitudeMode>GroundRelative</altitudeMode><name>11</name><meshId>dot6</meshId><movementSmoothing>0.05</movementSmoothing><maxNumberOfLocationUpdates>0</maxNumberOfLocationUpdates><useMovingAverage>false</useMovingAverage><hideObjectUtilItIsPlaced>true</hideObjectUtilItIsPlaced></Entry><Entry><id>90</id><lat>37.57950508340595</lat><lng>126.97669152058984</lng><altitude>0</altitude><altitudeMode>GroundRelative</altitudeMode><name>1rg</name><meshId>dot6</meshId><movementSmoothing>0.05</movementSmoothing><maxNumberOfLocationUpdates>0</maxNumberOfLocationUpdates><useMovingAverage>false</useMovingAverage><hideObjectUtilItIsPlaced>true</hideObjectUtilItIsPlaced></Entry><Entry><id>91</id><lat>37.57950725841876</lat><lng>126.97667148597168</lng><altitude>0</altitude><altitudeMode>GroundRelative</altitudeMode><name>ha</name><meshId>dot6</meshId><movementSmoothing>0.05</movementSmoothing><maxNumberOfLocationUpdates>0</maxNumberOfLocationUpdates><useMovingAverage>false</useMovingAverage><hideObjectUtilItIsPlaced>true</hideObjectUtilItIsPlaced></Entry><Entry><id>92</id><lat>37.57950747592038</lat><lng>126.9766525491383</lng><altitude>0</altitude><altitudeMode>GroundRelative</altitudeMode><name>gr</name><meshId>dot6</meshId><movementSmoothing>0.05</movementSmoothing><maxNumberOfLocationUpdates>0</maxNumberOfLocationUpdates><useMovingAverage>false</useMovingAverage><hideObjectUtilItIsPlaced>true</hideObjectUtilItIsPlaced></Entry><Entry><id>93</id><lat>37.579508699393756</lat><lng>126.97662652176592</lng><altitude>0</altitude><altitudeMode>GroundRelative</altitudeMode><name>sfb</name><meshId>dot6</meshId><movementSmoothing>0.05</movementSmoothing><maxNumberOfLocationUpdates>0</maxNumberOfLocationUpdates><useMovingAverage>false</useMovingAverage><hideObjectUtilItIsPlaced>true</hideObjectUtilItIsPlaced></Entry><Entry><id>94</id><lat>37.57950913999083</lat><lng>126.97660260970969</lng><altitude>0</altitude><altitudeMode>GroundRelative</altitudeMode><name>13g</name><meshId>dot6</meshId><movementSmoothing>0.05</movementSmoothing><maxNumberOfLocationUpdates>0</maxNumberOfLocationUpdates><useMovingAverage>false</useMovingAverage><hideObjectUtilItIsPlaced>true</hideObjectUtilItIsPlaced></Entry><Entry><id>95</id><lat>37.57950473399913</lat><lng>126.97658593104353</lng><altitude>0</altitude><altitudeMode>GroundRelative</altitudeMode><name>3t3</name><meshId>dot6</meshId><movementSmoothing>0.05</movementSmoothing><maxNumberOfLocationUpdates>0</maxNumberOfLocationUpdates><useMovingAverage>false</useMovingAverage><hideObjectUtilItIsPlaced>true</hideObjectUtilItIsPlaced></Entry><Entry><id>96</id><lat>37.57949460021773</lat><lng>126.97657314406399</lng><altitude>0</altitude><altitudeMode>GroundRelative</altitudeMode><name>y23</name><meshId>dot6</meshId><movementSmoothing>0.05</movementSmoothing><maxNumberOfLocationUpdates>0</maxNumberOfLocationUpdates><useMovingAverage>false</useMovingAverage><hideObjectUtilItIsPlaced>true</hideObjectUtilItIsPlaced></Entry><Entry><id>97</id><lat>37.57948094164091</lat><lng>126.97656424877562</lng><altitude>0</altitude><altitudeMode>GroundRelative</altitudeMode><name>3y2</name><meshId>dot6</meshId><movementSmoothing>0.05</movementSmoothing><maxNumberOfLocationUpdates>0</maxNumberOfLocationUpdates><useMovingAverage>false</useMovingAverage><hideObjectUtilItIsPlaced>true</hideObjectUtilItIsPlaced></Entry><Entry><id>98</id><lat>37.57946860485933</lat><lng>126.97655813326298</lng><altitude>0</altitude><altitudeMode>GroundRelative</altitudeMode><name>323</name><meshId>dot6</meshId><movementSmoothing>0.05</movementSmoothing><maxNumberOfLocationUpdates>0</maxNumberOfLocationUpdates><useMovingAverage>false</useMovingAverage><hideObjectUtilItIsPlaced>true</hideObjectUtilItIsPlaced></Entry><Entry><id>99</id><lat>37.57945714927423</lat><lng>126.9765497939311</lng><altitude>0</altitude><altitudeMode>GroundRelative</altitudeMode><name>235</name><meshId>dot6</meshId><movementSmoothing>0.05</movementSmoothing><maxNumberOfLocationUpdates>0</maxNumberOfLocationUpdates><useMovingAverage>false</useMovingAverage><hideObjectUtilItIsPlaced>true</hideObjectUtilItIsPlaced></Entry><Entry><id>100</id><lat>37.57944745608569</lat><lng>126.97654034268612</lng><altitude>0</altitude><altitudeMode>GroundRelative</altitudeMode><name>23y</name><meshId>dot6</meshId><movementSmoothing>0.05</movementSmoothing><maxNumberOfLocationUpdates>0</maxNumberOfLocationUpdates><useMovingAverage>false</useMovingAverage><hideObjectUtilItIsPlaced>true</hideObjectUtilItIsPlaced></Entry><Entry><id>101</id><lat>37.579448337285285</lat><lng>126.97652255210704</lng><altitude>0</altitude><altitudeMode>GroundRelative</altitudeMode><name>322</name><meshId>dot6</meshId><movementSmoothing>0.05</movementSmoothing><maxNumberOfLocationUpdates>0</maxNumberOfLocationUpdates><useMovingAverage>false</useMovingAverage><hideObjectUtilItIsPlaced>true</hideObjectUtilItIsPlaced></Entry><Entry><id>102</id><lat>37.57944745608569</lat><lng>126.97649531028298</lng><altitude>0</altitude><altitudeMode>GroundRelative</altitudeMode><name>237</name><meshId>dot6</meshId><movementSmoothing>0.05</movementSmoothing><maxNumberOfLocationUpdates>0</maxNumberOfLocationUpdates><useMovingAverage>false</useMovingAverage><hideObjectUtilItIsPlaced>true</hideObjectUtilItIsPlaced></Entry><Entry><id>103</id><lat>37.57944525308895</lat><lng>126.97647696374963</lng><altitude>0</altitude><altitudeMode>GroundRelative</altitudeMode><name>125</name><meshId>dot6</meshId><movementSmoothing>0.05</movementSmoothing><maxNumberOfLocationUpdates>0</maxNumberOfLocationUpdates><useMovingAverage>false</useMovingAverage><hideObjectUtilItIsPlaced>true</hideObjectUtilItIsPlaced></Entry><Entry><id>104</id><lat>37.57944877788462</lat><lng>126.97645917317044</lng><altitude>0</altitude><altitudeMode>GroundRelative</altitudeMode><name>23635</name><meshId>dot6</meshId><movementSmoothing>0.05</movementSmoothing><maxNumberOfLocationUpdates>0</maxNumberOfLocationUpdates><useMovingAverage>false</useMovingAverage><hideObjectUtilItIsPlaced>true</hideObjectUtilItIsPlaced></Entry><Entry><id>105</id><lat>37.57944877788407</lat><lng>126.97644249450008</lng><altitude>0</altitude><altitudeMode>GroundRelative</altitudeMode><name>326</name><meshId>dot6</meshId><movementSmoothing>0.05</movementSmoothing><maxNumberOfLocationUpdates>0</maxNumberOfLocationUpdates><useMovingAverage>false</useMovingAverage><hideObjectUtilItIsPlaced>true</hideObjectUtilItIsPlaced></Entry><Entry><id>106</id><lat>37.57944921848433</lat><lng>126.97642192414287</lng><altitude>0</altitude><altitudeMode>GroundRelative</altitudeMode><name>237235</name><meshId>dot6</meshId><movementSmoothing>0.05</movementSmoothing><maxNumberOfLocationUpdates>0</maxNumberOfLocationUpdates><useMovingAverage>false</useMovingAverage><hideObjectUtilItIsPlaced>true</hideObjectUtilItIsPlaced></Entry><Entry><id>107</id><lat>37.57944877788407</lat><lng>126.9764002418749</lng><altitude>0</altitude><altitudeMode>GroundRelative</altitudeMode><name>21</name><meshId>dot6</meshId><movementSmoothing>0.05</movementSmoothing><maxNumberOfLocationUpdates>0</maxNumberOfLocationUpdates><useMovingAverage>false</useMovingAverage><hideObjectUtilItIsPlaced>true</hideObjectUtilItIsPlaced></Entry><Entry><id>108</id><lat>37.579449659083636</lat><lng>126.97638467511729</lng><altitude>0</altitude><altitudeMode>GroundRelative</altitudeMode><name>834</name><meshId>dot6</meshId><movementSmoothing>0.05</movementSmoothing><maxNumberOfLocationUpdates>0</maxNumberOfLocationUpdates><useMovingAverage>false</useMovingAverage><hideObjectUtilItIsPlaced>true</hideObjectUtilItIsPlaced></Entry><Entry><id>109</id><lat>37.579448939606266</lat><lng>126.97636352527422</lng><altitude>0</altitude><altitudeMode>GroundRelative</altitudeMode><name>23622</name><meshId>dot6</meshId><movementSmoothing>0.05</movementSmoothing><maxNumberOfLocationUpdates>0</maxNumberOfLocationUpdates><useMovingAverage>false</useMovingAverage><hideObjectUtilItIsPlaced>true</hideObjectUtilItIsPlaced></Entry><Entry><id>110</id><lat>37.5794493802056</lat><lng>126.97634406683005</lng><altitude>0</altitude><altitudeMode>GroundRelative</altitudeMode><name>2362</name><meshId>dot6</meshId><movementSmoothing>0.05</movementSmoothing><maxNumberOfLocationUpdates>0</maxNumberOfLocationUpdates><useMovingAverage>false</useMovingAverage><hideObjectUtilItIsPlaced>true</hideObjectUtilItIsPlaced></Entry><Entry><id>111</id><lat>37.579470088379466</lat><lng>126.9763423989628</lng><altitude>0</altitude><altitudeMode>GroundRelative</altitudeMode><name>12312</name><meshId>dot6</meshId><movementSmoothing>0.05</movementSmoothing><maxNumberOfLocationUpdates>0</maxNumberOfLocationUpdates><useMovingAverage>false</useMovingAverage><hideObjectUtilItIsPlaced>true</hideObjectUtilItIsPlaced></Entry><Entry><id>112</id><lat>37.579489474748485</lat><lng>126.97634351087356</lng><altitude>0</altitude><altitudeMode>GroundRelative</altitudeMode><name>1123</name><meshId>dot6</meshId><movementSmoothing>0.05</movementSmoothing><maxNumberOfLocationUpdates>0</maxNumberOfLocationUpdates><useMovingAverage>false</useMovingAverage><hideObjectUtilItIsPlaced>true</hideObjectUtilItIsPlaced></Entry><Entry><id>113</id><lat>37.579507988780364</lat><lng>126.97634382464065</lng><altitude>0</altitude><altitudeMode>GroundRelative</altitudeMode><name>2444</name><meshId>dot6</meshId><movementSmoothing>0.05</movementSmoothing><maxNumberOfLocationUpdates>0</maxNumberOfLocationUpdates><useMovingAverage>false</useMovingAverage><hideObjectUtilItIsPlaced>true</hideObjectUtilItIsPlaced></Entry><Entry><id>114</id><lat>37.57953930743153</lat><lng>126.97634382464065</lng><altitude>0</altitude><altitudeMode>GroundRelative</altitudeMode><name>23124</name><meshId>dot6</meshId><movementSmoothing>0.05</movementSmoothing><maxNumberOfLocationUpdates>0</maxNumberOfLocationUpdates><useMovingAverage>false</useMovingAverage><hideObjectUtilItIsPlaced>true</hideObjectUtilItIsPlaced></Entry><Entry><id>115</id><lat>37.57956345431744</lat><lng>126.9763427411558</lng><altitude>0</altitude><altitudeMode>GroundRelative</altitudeMode><name>23236</name><meshId>dot6</meshId><movementSmoothing>0.05</movementSmoothing><maxNumberOfLocationUpdates>0</maxNumberOfLocationUpdates><useMovingAverage>false</useMovingAverage><hideObjectUtilItIsPlaced>true</hideObjectUtilItIsPlaced></Entry><Entry><id>116</id><lat>37.579587545570135</lat><lng>126.97634679432775</lng><altitude>0</altitude><altitudeMode>GroundRelative</altitudeMode><name>2377</name><meshId>dot6</meshId><movementSmoothing>0.05</movementSmoothing><maxNumberOfLocationUpdates>0</maxNumberOfLocationUpdates><useMovingAverage>false</useMovingAverage><hideObjectUtilItIsPlaced>true</hideObjectUtilItIsPlaced></Entry><Entry><id>117</id><lat>37.57961083377397</lat><lng>126.97634679432775</lng><altitude>0</altitude><altitudeMode>GroundRelative</altitudeMode><name>3623</name><meshId>dot6</meshId><movementSmoothing>0.05</movementSmoothing><maxNumberOfLocationUpdates>0</maxNumberOfLocationUpdates><useMovingAverage>false</useMovingAverage><hideObjectUtilItIsPlaced>true</hideObjectUtilItIsPlaced></Entry><Entry><id>118</id><lat>37.57962689460001</lat><lng>126.97634882091273</lng><altitude>0</altitude><altitudeMode>GroundRelative</altitudeMode><name>36235</name><meshId>dot6</meshId><movementSmoothing>0.05</movementSmoothing><maxNumberOfLocationUpdates>0</maxNumberOfLocationUpdates><useMovingAverage>false</useMovingAverage><hideObjectUtilItIsPlaced>true</hideObjectUtilItIsPlaced></Entry><Entry><id>119</id><lat>37.57965018279154</lat><lng>126.97634983420522</lng><altitude>0</altitude><altitudeMode>GroundRelative</altitudeMode><name>235235</name><meshId>dot6</meshId><movementSmoothing>0.05</movementSmoothing><maxNumberOfLocationUpdates>0</maxNumberOfLocationUpdates><useMovingAverage>false</useMovingAverage><hideObjectUtilItIsPlaced>true</hideObjectUtilItIsPlaced></Entry></ArGpsLocationData>